IS623_ImageTools/ImageProcessor.py
IS623_ImageTools/SimpleImageViewer.py
IS623_ImageTools/__init__.py
is623_imagetools-1.0.0.dist-info/METADATA
is623_imagetools-1.0.0.dist-info/WHEEL
is623_imagetools-1.0.0.dist-info/top_level.txt
is623_imagetools-1.0.0.dist-info/RECORD
