Metadata-Version: 2.2
Name: IS623_ImageTools
Version: 1.0.0
Summary: A simple library for image processing and visualization for the IS623 - Computación Gráfica course at Universidad Tecnológica de Pereira (UTP), developed by Kevin Esguerra Cardona.
Home-page: https://github.com/porgetit/IS623-ImageTools.git
Author: Kevin Esguerra Cardona
Author-email: kevin.esguerra@utp.edu.co
Requires-Dist: numpy
Requires-Dist: matplotlib
Requires-Dist: Pillow
Dynamic: author
Dynamic: author-email
Dynamic: description
Dynamic: description-content-type
Dynamic: home-page
Dynamic: requires-dist
Dynamic: summary
